setup.py
clc/__init__.py
clc/defaults.py
clc/APIv1/__init__.py
clc/APIv1/account.py
clc/APIv1/api.py
clc/APIv1/billing.py
clc/APIv1/blueprint.py
clc/APIv1/cli.py
clc/APIv1/exceptions.py
clc/APIv1/group.py
clc/APIv1/network.py
clc/APIv1/output.py
clc/APIv1/queue.py
clc/APIv1/server.py
clc/APIv1/shell.py
clc/APIv1/terminal_size.py
clc/APIv1/user.py
clc/APIv2/__init__.py
clc/APIv2/account.py
clc/APIv2/alert.py
clc/APIv2/anti_affinity.py
clc/APIv2/api.py
clc/APIv2/datacenter.py
clc/APIv2/disk.py
clc/APIv2/group.py
clc/APIv2/horizontal_autoscale.py
clc/APIv2/network.py
clc/APIv2/public_ip.py
clc/APIv2/queue.py
clc/APIv2/server.py
clc/APIv2/template.py
clc/APIv2/time_utils.py
clc_sdk.egg-info/PKG-INFO
clc_sdk.egg-info/SOURCES.txt
clc_sdk.egg-info/dependency_links.txt
clc_sdk.egg-info/entry_points.txt
clc_sdk.egg-info/requires.txt
clc_sdk.egg-info/top_level.txt